azureml_ngc_tools/AzureMLComputeCluster.py
azureml_ngc_tools/__init__.py
azureml_ngc_tools/_version.py
azureml_ngc_tools/cli/__init__.py
azureml_ngc_tools/cli/azcli_utils.py
azureml_ngc_tools/cli/azureml_ngc.py
azureml_ngc_tools/cli/ngccontent.py
azureml_ngc_tools/cli/utilities.py
azureml_ngc_tools/setup/__init__.py
azureml_ngc_tools/setup/start_jupyter.py
azureml_ngc_tools/utils/__init__.py
azureml_ngc_tools/utils/port_forward_utils.py
azureml_ngc_tools-1.5.1.dist-info/METADATA
azureml_ngc_tools-1.5.1.dist-info/WHEEL
azureml_ngc_tools-1.5.1.dist-info/entry_points.txt
azureml_ngc_tools-1.5.1.dist-info/top_level.txt
azureml_ngc_tools-1.5.1.dist-info/RECORD
