Metadata-Version: 2.1
Name: azureml-ngc-tools
Version: 1.5.1
Summary: AzureML integration with NGC
Home-page: 
License: BSD
Keywords: azureml,ngc,gpu
Requires-Python: >=3.5
Requires-Dist: azureml-sdk (==1.25.0)
Requires-Dist: PyJWT (<2.0.0)
Requires-Dist: click (>=7.1.2)
Requires-Dist: tqdm (>=4.48.0)
Requires-Dist: progressbar2 (>=3.53.1)
Requires-Dist: nbformat (==5.4.0)
